LICENSE
MANIFEST.in
README.md
requirements.txt
settings.py
setup.py
meetg/__init__.py
meetg/api_methods.py
meetg/api_types.py
meetg/botting.py
meetg/default_settings.py
meetg/factories.py
meetg/loging.py
meetg/manage.py
meetg/scripts.py
meetg/stats.py
meetg/storage.py
meetg/testing.py
meetg/utils.py
meetg.egg-info/PKG-INFO
meetg.egg-info/SOURCES.txt
meetg.egg-info/dependency_links.txt
meetg.egg-info/entry_points.txt
meetg.egg-info/requires.txt
meetg.egg-info/top_level.txt